licensekeygentest/__init__.py
licensekeygentest/main.py
licensekeygentest-1.1.4.dist-info/LICENSE
licensekeygentest-1.1.4.dist-info/METADATA
licensekeygentest-1.1.4.dist-info/WHEEL
licensekeygentest-1.1.4.dist-info/top_level.txt
licensekeygentest-1.1.4.dist-info/RECORD
