Metadata-Version: 2.1
Name: licensekeygentest
Version: 1.1.4
Summary: POC for license validation checks
Author: Rahul R
Author-email: <rahulranjan25.RR@gmail.com>
Keywords: python,authentication,licensing
Classifier: Development Status :: 1 - Planning
Classifier: Intended Audience :: Developers
Classifier: Programming Language :: Python :: 3
Classifier: Operating System :: Unix
Classifier: Operating System :: MacOS :: MacOS X
Classifier: Operating System :: Microsoft :: Windows
License-File: LICENSE
Requires-Dist: requests
